memrun/__init__.py
memrun/cli.py
memrun/commands/__init__.py
memrun/commands/deploy.py
memrun/commands/logs.py
memrun/commands/queue.py
memrun/commands/scale.py
memrun/commands/servers.py
memrun/commands/status.py
memrun/context.py
memrun/decorators.py
memrun/deploy.py
memrun/handler_builder.py
memrun/handler_extractor.py
memrun/local.py
memrun/py.typed
memrun/service.py
memrun-0.1.6.dist-info/WHEEL
memrun-0.1.6.dist-info/entry_points.txt
memrun-0.1.6.dist-info/METADATA
memrun-0.1.6.dist-info/RECORD
