Metadata-Version: 2.3
Name: memrun
Version: 0.1.6
Summary: Serverless data platform SDK and CLI for Hetzner Cloud
Author: Julian Mulla
Author-email: Julian Mulla <jmulla@gmail.com>
Requires-Dist: mem-common
Requires-Dist: mem-storage
Requires-Dist: httpx>=0.27
Requires-Dist: pydantic>=2.0
Requires-Dist: typer>=0.12
Requires-Dist: rich>=13.0
Requires-Dist: tomli>=2.0
Requires-Python: >=3.11
